{"type":"url-img","imgUrl":"https://live.staticflickr.com/4111/5200715220_eda68430cd_b.jpg","classification":{"title":"Bathroom Wallpaper","tags":["design","graphic","illustration","textile","art","desktop","geometric","pattern","repetition","seamless","abstract","background","decoration","element","ornate","retro","texture","wallpaper","fabric","vintage"],"description":null,"author":"Sam Howzit","authot_link":"https://www.flickr.com/photos/12508217@N08","license":"by-2.0","license_link":"https://creativecommons.org/licenses/by/2.0/"}}