{"type":"url-img","imgUrl":"https://live.staticflickr.com/7107/7603880226_bbfca64f86.jpg","thumbUrl":"http://api.openverse.engineering/v1/images/6e7cb7df-3a44-4b59-aa1c-9c9c2a6fdb79/thumb/","classification":{"title":"Free Space Waves Stock BackgroundsEtc Wallpaper - Deep Maroon","tags":["abstract","art","bright","dark","design","sunset","texture"],"description":null,"author":"webtreats","authot_link":"https://www.flickr.com/photos/44071822@N08","license":"by-2.0","license_link":"https://creativecommons.org/licenses/by/2.0/"}}