{"type":"url-img","imgUrl":"https://live.staticflickr.com/6184/6145146945_9086fb3d21.jpg","classification":{"title":"Free Grunge Warning Stripes Stock BackgroundsEtc Wallpaper - Deep Maroon","tags":["backgroundsetc","deep","grunge","maroon","mysitemywaycom","stockgraphics","stockpattern","stripes","tileable","wallpapers","warning","webbackgrounds","abstract","background","design","desktop","fabric","old","pattern","rough","surface","textile","texture","wallpaper","weaving"],"description":null,"author":"webtreats","authot_link":"https://www.flickr.com/photos/44071822@N08","license":"by-2.0","license_link":"https://creativecommons.org/licenses/by/2.0/"}}