{"type":"url-img","imgUrl":"https://live.staticflickr.com/7156/6501911257_87419ff76e.jpg","thumbUrl":"http://api.openverse.engineering/v1/images/94495ccf-df98-4286-86d4-d62260d8cd40/thumb/","classification":{"title":"Free Polka Dots And Squares Stock BackgroundsEtc Wallpaper - Deep Green Orange","tags":["abstract","art","color","design","futuristic","pattern","texture"],"description":null,"author":"webtreats","authot_link":"https://www.flickr.com/photos/44071822@N08","license":"by-2.0","license_link":"https://creativecommons.org/licenses/by/2.0/"}}