{"type":"url-img","imgUrl":"https://live.staticflickr.com/8439/7991018519_6b0e09ff94_b.jpg","thumbUrl":"http://api.openverse.engineering/v1/images/26ee1d38-7b18-4d08-871d-f26dd1cce9eb/thumb/","classification":{"file":"openverse/media/26ee1d38-7b18-4d08-871d-f26dd1cce9eb/head.json","title":"Brisbane Lightshow Widescreen Wallpaper","tags":["light","dark","dusk","evening","landscape","light","sky","skyline"],"description":""},"author":"James Niland","authot_link":"https://www.flickr.com/photos/25027666@N02","license":"by-2.0","license_link":"https://creativecommons.org/licenses/by/2.0/"}