{"id":0,"type":"url","imgUrl":"https://live.staticflickr.com/3433/3248450146_a5ea1a4643_b.jpg","classification":{"title":"geology - desktop background wallpaper","tags":["2560x1600wallpaper","background","bed","desktop","download","formation","free","geology","hd","layer","mac","osx","rock","texture","vista","wallpaper","widescreen","windows","windows7","xp"],"description":null,"author":"(matt)","authot_link":"https://www.flickr.com/photos/83646108@N00","license":"by-nd-2.0","license_link":"https://creativecommons.org/licenses/by-nd/2.0/"}}