{"type":"url-img","imgUrl":"https://live.staticflickr.com/8084/8328458419_715670bcb9_b.jpg","thumbUrl":"http://api.openverse.engineering/v1/images/3bcfef96-9ebc-48ba-bfc9-a2b4e743dfcf/thumb/","classification":{"file":"openverse/media/3bcfef96-9ebc-48ba-bfc9-a2b4e743dfcf/head.json","title":"wallpaper chrismas 1920x1200 greeting christmas deliver holiday backgrounds","tags":[],"description":null},"author":"22860","authot_link":"https://www.flickr.com/photos/52193079@N03","license":"by-sa-2.0","license_link":"https://creativecommons.org/licenses/by-sa/2.0/"}