{"type":"url-img","imgUrl":"https://live.staticflickr.com/4578/24738905818_a1319e82de_b.jpg","thumbUrl":"http://api.openverse.engineering/v1/images/a504aa5b-3961-46d9-9f76-d9f4c2cac871/thumb/","classification":{"file":"openverse/media/a504aa5b-3961-46d9-9f76-d9f4c2cac871/head.json","title":"ETC Wallpaper - Illuminated Skyscraper","tags":[],"description":""},"author":"EthereumClassic","authot_link":"https://www.flickr.com/photos/149639283@N08","license":"cc0-1.0","license_link":"https://creativecommons.org/publicdomain/zero/1.0/"}