{"type":"url-img","imgUrl":"https://live.staticflickr.com/3618/3363379182_2bcecd158a_b.jpg","classification":{"title":"cone - desktop background wallpaper","tags":["2560x1600wallpaper","background","beach","desktop","download","free","hd","mac","ocean","osx","pinecone","rock","sand","surf","vista","wallpaper","water","wave","widescreen","windows","windows7","xp"],"description":null,"author":"(matt)","authot_link":"https://www.flickr.com/photos/83646108@N00","license":"by-nd-2.0","license_link":"https://creativecommons.org/licenses/by-nd/2.0/"}}