{"type":"url-img","imgUrl":"https://live.staticflickr.com/4040/4610331145_c2e33034bb_b.jpg","thumbUrl":"http://api.openverse.engineering/v1/images/112c7aa2-dffb-4922-b74a-ee81c3240be7/thumb/","classification":{"file":"openverse/media/112c7aa2-dffb-4922-b74a-ee81c3240be7/head.json","title":"Piano roll wallpaper, toilet, Ace Hotel, Portland, OR, USA3.JPG","tags":[],"description":""},"author":"gruntzooki","authot_link":"https://www.flickr.com/photos/37996580417@N01","license":"by-sa-2.0","license_link":"https://creativecommons.org/licenses/by-sa/2.0/"}