{"type":"url-img","imgUrl":"https://live.staticflickr.com/7457/27948986856_7b43d2d36f_b.jpg","thumbUrl":"http://api.openverse.engineering/v1/images/212b6507-30b1-4567-95de-ef81f93343b5/thumb/","classification":{"file":"openverse/media/212b6507-30b1-4567-95de-ef81f93343b5/head.json","title":"Abstract Hipster Wallpaper - Revrsed","tags":[],"description":""},"author":"Douglas Tofoli","authot_link":"https://www.flickr.com/photos/141973883@N05","license":"pdm-1.0","license_link":"https://creativecommons.org/publicdomain/mark/1.0/"}