{"type":"url-img","imgUrl":"https://live.staticflickr.com/5214/5472638767_0775c62a70_b.jpg","thumbUrl":"http://api.openverse.engineering/v1/images/e54474aa-198e-421f-995c-2ee59b14d398/thumb/","classification":{"file":"openverse/media/e54474aa-198e-421f-995c-2ee59b14d398/head.json","title":"T-Shirt Sprüche als Schreibtischhintergrund (Wallpaper) in HD","tags":[],"description":""},"author":"LoboStudio Hamburg","authot_link":"https://www.flickr.com/photos/39713146@N08","license":"by-sa-2.0","license_link":"https://creativecommons.org/licenses/by-sa/2.0/"}