{"type":"url-img","imgUrl":"https://live.staticflickr.com/31/41230966_d34c7eddfb_b.jpg","thumbUrl":"http://api.openverse.engineering/v1/images/0e66dc54-42f8-4897-835a-6d27d12c0513/thumb/","classification":{"file":"openverse/media/0e66dc54-42f8-4897-835a-6d27d12c0513/head.json","title":"iPod nano wallpaper v1.1","tags":[],"description":null},"author":"Noeluap","authot_link":"https://www.flickr.com/photos/90516586@N00","license":"by-sa-2.0","license_link":"https://creativecommons.org/licenses/by-sa/2.0/"}