{"type":"url-img","imgUrl":"https://live.staticflickr.com/7146/6597570981_9ed35ebe4a.jpg","thumbUrl":"http://api.openverse.engineering/v1/images/c72e1ab9-ddec-46bf-ab45-839fc5390adf/thumb/","classification":{"file":"openverse/media/c72e1ab9-ddec-46bf-ab45-839fc5390adf/head.json","title":"Free Urban Circles Stock BackgroundsEtc Wallpaper - Green Yellow Orange","tags":["abstract","art","design","pattern","retro","texture"],"description":""},"author":"webtreats","authot_link":"https://www.flickr.com/photos/44071822@N08","license":"by-2.0","license_link":"https://creativecommons.org/licenses/by/2.0/"}