{"type":"url-img","imgUrl":"https://live.staticflickr.com/3014/3007569431_1417553320_b.jpg","classification":{"title":"arnicio wallpaper 4-3","tags":["asturias","asturies","background","caso","d300","escritorio","espagne","espanha","espau00f1a","europa","europe","fondo","landscape","nikon","paisaje","spain","tamron1750mm","wallpaper","agriculture","cropland","grassland","hill","landscape","mountain","nature","outdoors","scenic","sky","travel","tree","valley","wood"],"description":null,"author":"R.Duran","authot_link":"https://www.flickr.com/photos/45327189@N00","license":"by-2.0","license_link":"https://creativecommons.org/licenses/by/2.0/"}}