{"type":"url-img","imgUrl":"https://live.staticflickr.com/8140/29749867363_a34d05e18f_b.jpg","thumbUrl":"http://api.openverse.engineering/v1/images/e7b5b206-a75b-4e44-a0f3-d09257ee1c8c/thumb/","classification":{"file":"openverse/media/e7b5b206-a75b-4e44-a0f3-d09257ee1c8c/head.json","title":"Money Desktop Wallpapers","tags":[],"description":null},"author":"ibanksaibanksa","authot_link":"https://www.flickr.com/photos/148182869@N03","license":"pdm-1.0","license_link":"https://creativecommons.org/publicdomain/mark/1.0/"}