{"id":0,"type":"url","imgUrl":"https://live.staticflickr.com/8441/7777360682_b8753b7871_b.jpg","classification":{"title":"Karatoa River Catch HD Images wallpaper picture on rainy season Inside Ghoraghat,Dinajpur,Bangladesh","tags":["gethdimagecom","karatoarivercatchhdimageswallpaperpictureonrainyseasoninsideghoraghatdinajpurbangladesh","bridge","dam","environment","flood","lake","landscape","nature","outdoors","recreation","reflection","reservoir","river","riverbank","sky","summer","travel","tree","water","wood"],"description":null,"author":"Gethdimage.com","authot_link":"https://www.flickr.com/photos/72671518@N04","license":"by-2.0","license_link":"https://creativecommons.org/licenses/by/2.0/"}}