{"id":0,"type":"url","imgUrl":"https://live.staticflickr.com/8013/7532299728_414dca91ac.jpg","classification":{"title":"Free Knitted Yarn Stock BackgroundsEtc Wallpaper - Purple","tags":["backgroundsetc","knitted","mysitemywaycom","purple","stockgraphics","stockpattern","tileable","wallpapers","webbackgrounds","yarn","abstract","background","canvas","color","cotton","design","desktop","fabric","fashion","fiber","linen","luxury","pattern","rough","surface","textile","texture","wallpaper","wear","weaving"],"description":null,"author":"webtreats","authot_link":"https://www.flickr.com/photos/44071822@N08","license":"by-2.0","license_link":"https://creativecommons.org/licenses/by/2.0/"}}