{"id":0,"type":"url","imgUrl":"https://live.staticflickr.com/3423/3360560410_5d60681a1b.jpg","classification":{"title":"poopie flower wallpaper bg","tags":["background","flower","green","poopie","spring","wallpaper","art","birthday","cute","decoration","design","fun","funny","graphic","graphic design","heart","illustration","love","pattern","retro","sketch","vector","wallpaper"],"description":null,"author":"jelene","authot_link":"https://www.flickr.com/photos/70831250@N00","license":"by-2.0","license_link":"https://creativecommons.org/licenses/by/2.0/"}}