{"id":0,"type":"url","imgUrl":"https://live.staticflickr.com/7052/6866445855_e88efe80d3.jpg","classification":{"title":"Free Retro Squares Stock BackgroundsEtc Wallpaper - Burnt Orange Gray","tags":["backgroundsetc","burnt","gray","mysitemywaycom","orange","retrosquares","stockgraphics","stockpattern","tileable","wallpapers","webbackgrounds","abstract","art","background","decoration","design","desktop","fabric","illustration","old","paper","pattern","retro","texture","vintage","wall","wallpaper"],"description":null,"author":"webtreats","authot_link":"https://www.flickr.com/photos/44071822@N08","license":"by-2.0","license_link":"https://creativecommons.org/licenses/by/2.0/"}}