{"type":"url-img","imgUrl":"https://live.staticflickr.com/4132/5017238940_60b60bf4e3_b.jpg","thumbUrl":"http://api.openverse.engineering/v1/images/2c471810-7b3d-43e0-aa8b-0409da0d53b6/thumb/","classification":{"file":"openverse/media/2c471810-7b3d-43e0-aa8b-0409da0d53b6/head.json","title":"T-Shirt Sprüche als Schreibtischhintergrund (Wallpaper) in HD","tags":[],"description":""},"author":"LoboStudio Hamburg","authot_link":"https://www.flickr.com/photos/39713146@N08","license":"by-sa-2.0","license_link":"https://creativecommons.org/licenses/by-sa/2.0/"}