{"type":"url-img","imgUrl":"https://live.staticflickr.com/121/277522703_bca7a89731_b.jpg","classification":{"title":"April 2007 desktop wallpaper","tags":["1024x768","2007","beltain","beltane","bonfire","burning","butserancientfarm","calendar","champion","desktop","hampshire","jim","jimchampion","spring","treehouse1977","wallpaper","wickerman"],"description":null,"author":"treehouse1977","authot_link":"https://www.flickr.com/photos/13071852@N00","license":"by-sa-2.0","license_link":"https://creativecommons.org/licenses/by-sa/2.0/"}}