{"type":"url-img","imgUrl":"https://live.staticflickr.com/5115/5868380768_61e3af4dc9.jpg","thumbUrl":"http://api.openverse.engineering/v1/images/953a9fe0-9114-466b-a97d-6eaac22b122a/thumb/","classification":{"title":"Free Curtain Stock BackgroundsEtc Wallpaper - Light Pink","tags":["light","abstract","art","bright","color","design","pattern","retro","texture"],"description":null},"author":"webtreats","authot_link":"https://www.flickr.com/photos/44071822@N08","license":"by-2.0","license_link":"https://creativecommons.org/licenses/by/2.0/"}