{"type":"url-img","imgUrl":"https://live.staticflickr.com/4147/5016631951_ee15b8a898_b.jpg","thumbUrl":"http://api.openverse.engineering/v1/images/3249ef8a-65bf-4b44-b6d6-c6eb760c1941/thumb/","classification":{"file":"openverse/media/3249ef8a-65bf-4b44-b6d6-c6eb760c1941/head.json","title":"T-Shirt Sprüche als Schreibtischhintergrund (Wallpaper) in HD","tags":[],"description":null},"author":"LoboStudio Hamburg","authot_link":"https://www.flickr.com/photos/39713146@N08","license":"by-sa-2.0","license_link":"https://creativecommons.org/licenses/by-sa/2.0/"}