{"type":"url-img","imgUrl":"https://live.staticflickr.com/3286/3151979647_062cee2c55_b.jpg","thumbUrl":"http://api.openverse.engineering/v1/images/b008553a-c0c0-4829-946b-da36682be234/thumb/","classification":{"file":"openverse/media/b008553a-c0c0-4829-946b-da36682be234/head.json","title":"golden gate - desktop background wallpaper","tags":[],"description":""},"author":"(matt)","authot_link":"https://www.flickr.com/photos/83646108@N00","license":"by-nd-2.0","license_link":"https://creativecommons.org/licenses/by-nd/2.0/"}